{
  "db_name": "PostgreSQL",
  "query": "\n            SELECT id, name, email, role as \"role: crate::domain::user::UserRole\", created_at\n            FROM users\n            WHERE id = $1\n            ",
  "describe": {
    "columns": [
      {
        "ordinal": 0,
        "name": "id",
        "type_info": "Uuid"
      },
      {
        "ordinal": 1,
        "name": "name",
        "type_info": "Text"
      },
      {
        "ordinal": 2,
        "name": "email",
        "type_info": "Text"
      },
      {
        "ordinal": 3,
        "name": "role: crate::domain::user::UserRole",
        "type_info": {
          "Custom": {
            "name": "user_role",
            "kind": {
              "Enum": [
                "user",
                "admin"
              ]
            }
          }
        }
      },
      {
        "ordinal": 4,
        "name": "created_at",
        "type_info": "Timestamptz"
      }
    ],
    "parameters": {
      "Left": [
        "Uuid"
      ]
    },
    "nullable": [
      false,
      false,
      false,
      false,
      false
    ]
  },
  "hash": "dcfc23b5c082b1f4d706aab4633f10a827e86e2bd01bcebf4c9bc5d18e4f413d"
}
